timer_context/__init__.py
timer_context/context.py
timer_context-0.1.0.dist-info/LICENSE
timer_context-0.1.0.dist-info/METADATA
timer_context-0.1.0.dist-info/WHEEL
timer_context-0.1.0.dist-info/top_level.txt
timer_context-0.1.0.dist-info/RECORD
