Metadata-Version: 2.2
Name: timer-context
Version: 0.1.0
Summary: A simple context manager for timing blocks of Python code.
Author-email: Andrew Sansom <andrew@euleriancircuit.com>
License: MIT
Project-URL: Homepage, https://github.com/qthequartermasterman/timer-context
Project-URL: Bug Tracker, https://github.com/qthequartermasterman/timer-context/issues
Keywords: timing,performance,context-manager,python
Classifier: Development Status :: 5 - Production/Stable
Classifier: Intended Audience :: Developers
Classifier: License :: OSI Approved :: MIT License
Classifier: Programming Language :: Python :: 3
Classifier: Programming Language :: Python :: 3.9
Classifier: Programming Language :: Python :: 3.10
Classifier: Programming Language :: Python :: 3.11
Classifier: Programming Language :: Python :: 3.12
Classifier: Programming Language :: Python :: 3.13
Classifier: Topic :: Software Development :: Libraries :: Python Modules
Classifier: Topic :: System :: Benchmark
Requires-Python: >=3.7
License-File: LICENSE
Provides-Extra: lint
Requires-Dist: mypy==1.14.1; extra == "lint"
Requires-Dist: ruff==0.9.3; extra == "lint"
Requires-Dist: toml-sort==0.24.2; extra == "lint"
Provides-Extra: test
Requires-Dist: hypothesis==6.124.2; extra == "test"
Requires-Dist: pytest==8.3.4; extra == "test"
Requires-Dist: pytest-cov==6.0.0; extra == "test"
